rabbitmq_provider/__init__.py
rabbitmq_provider/hooks/__init__.py
rabbitmq_provider/hooks/rabbitmq.py
rabbitmq_provider/operators/__init__.py
rabbitmq_provider/operators/rabbitmq.py
rabbitmq_provider/sensors/__init__.py
rabbitmq_provider/sensors/rabbitmq.py
airflow_provider_rabbitmq-0.6.1.dist-info/entry_points.txt
airflow_provider_rabbitmq-0.6.1.dist-info/LICENSE
airflow_provider_rabbitmq-0.6.1.dist-info/WHEEL
airflow_provider_rabbitmq-0.6.1.dist-info/METADATA
airflow_provider_rabbitmq-0.6.1.dist-info/RECORD
