Metadata-Version: 2.1
Name: airflow-provider-rabbitmq
Version: 0.6.1
Summary: A RabbitMQ provider for Apache Airflow
Author: Tes Engineering
Author-email: engineering@tesglobal.com
Requires-Python: >=3.7,<4.0
Classifier: Programming Language :: Python :: 3
Classifier: Programming Language :: Python :: 3.10
Classifier: Programming Language :: Python :: 3.7
Classifier: Programming Language :: Python :: 3.8
Classifier: Programming Language :: Python :: 3.9
Requires-Dist: apache-airflow (>=1.10)
Requires-Dist: pika (>=1.2.0,<2.0.0)
Requires-Dist: whippet (>=0.3.2,<0.4.0)
